{
  "_fv": 39,
  "_type": "tool",
  "definition": {
    "renderType": 0,
    "texture": "emerladaxe",
    "customModelName": "Normal",
    "name": "Emerald Axe",
    "specialInfo": [],
    "creativeTab": {
      "value": "TOOLS"
    },
    "toolType": "Axe",
    "harvestLevel": 1,
    "efficiency": 8.0,
    "attackSpeed": 1.0,
    "enchantability": 12,
    "damageVsEntity": 9.0,
    "usageCount": 1200,
    "blocksAffected": [],
    "hasGlow": false,
    "repairItems": [
      {
        "value": "Items.EMERALD"
      }
    ],
    "immuneToFire": false,
    "stayInGridWhenCrafting": false,
    "damageOnCrafting": false
  }
}